tonicnet/__init__.py
tonicnet-0.1.3.dist-info/METADATA
tonicnet-0.1.3.dist-info/WHEEL
tonicnet-0.1.3.dist-info/RECORD
