Metadata-Version: 2.1
Name: tonicnet
Version: 0.1.3
Summary: 
Author: abraao
Requires-Python: >=3.10,<4.0
Classifier: Programming Language :: Python :: 3
Classifier: Programming Language :: Python :: 3.10
Classifier: Programming Language :: Python :: 3.11
Requires-Dist: music21 (>=9.1.0,<10.0.0)
Requires-Dist: torch (>=2.0.1,<3.0.0)
